{
   "currentProfile": 0,
   "profiles": [
      {
         "id": 0,
         "name": "default",
         "collection": [
            { 
            "card": {
               "id": "A1-001",
               "name": "Bulbasaur",
               "image":"https://assets.tcgdex.net/en/tcgp/A1/001/low.png"
               },
            "quantity": 3
            },
            {
            "card": {
               "id": "A1-002",
               "name": "Ivysaur",
               "image":"https://assets.tcgdex.net/en/tcgp/A1/002/low.png"
               },
            "quantity": 2
            },
            {
            "card": {
               "id": "A1-002",
               "name": "Ivysaur",
               "image":"https://assets.tcgdex.net/en/tcgp/A1/002/low.png"
               },
            "quantity": 2
            },
            {
            "card": {
               "id": "A1-002",
               "name": "Ivysaur",
               "image":"https://assets.tcgdex.net/en/tcgp/A1/002/low.png"
               },
            "quantity": 2
            },
            {
            "card": {
               "id": "A1-002",
               "name": "Ivysaur",
               "image":"https://assets.tcgdex.net/en/tcgp/A1/002/low.png"
               },
            "quantity": 2
            }
         ],
         "settings": {
            "language": "en",
            "theme": "LIGHT"
         }
      },

      {
         "id": 1,
         "name": "Profile 1",
         "collection": [
            { 
            "card": {
               "id": "A2b-007",
               "name": "Meowscarada",
               "image":"https://assets.tcgdex.net/en/tcgp/A2b/007/low.png"
               },
            "quantity": 2
            }
         ],
         "settings": {
            "language": "en",
            "theme": "DARK"
         }
      }
   ]
}